[{"line":4,"elements":[{"line":6,"name":"","description":"","type":"background","keyword":"Contexto","steps":[{"result":{"duration":1634783200,"status":"passed"},"line":7,"name":"que estou na pagina do recupera","match":{"location":"recupera.steps.ConsultaStep.queEstouNaPaginaDoRecupera()"},"keyword":"Dado "}]},{"start_timestamp":"2025-03-11T20:38:26.878Z","before":[{"result":{"duration":4348501200,"status":"passed"},"match":{"location":"recupera.steps.hooks.hook.setUp()"}}],"line":10,"name":"Fazer consulta de cliente com divida","description":"","id":"consulta-cliente;fazer-consulta-de-cliente-com-divida","after":[{"result":{"duration":258598900,"status":"passed"},"match":{"location":"recupera.steps.hooks.hook.finish()"}}],"type":"scenario","keyword":"Cenario","steps":[{"result":{"duration":793118000,"status":"passed"},"line":11,"name":"Clico em operacao","match":{"location":"recupera.steps.ConsultaStep.clicoEmOperacao()"},"keyword":"Quando "},{"result":{"duration":2283757200,"status":"passed"},"line":12,"name":"pesquiso pelo cliente","match":{"location":"recupera.steps.ConsultaStep.pesquisoPeloCliente()"},"keyword":"E "},{"result":{"duration":679015800,"status":"passed"},"line":13,"name":"consulta realizada com sucesso","match":{"location":"recupera.steps.ConsultaStep.consultaRealizadaComSucesso()"},"keyword":"Entao "}],"tags":[{"name":"@ConsultaExecution"},{"name":"@CenarioComum"}]}],"name":"Consulta Cliente","description":"","id":"consulta-cliente","keyword":"Funcionalidade","uri":"file:src/test/resources/features/Consulta.feature","tags":[{"name":"@ConsultaExecution","type":"Tag","location":{"line":3,"column":1}}]},{"line":4,"elements":[{"line":6,"name":"","description":"","type":"background","keyword":"Contexto","steps":[{"result":{"duration":266336600,"status":"passed"},"line":7,"name":"que estou na pagina de login","match":{"location":"recupera.steps.HomeStep.queEstouNaPaginaDeLogin()"},"keyword":"Dado "}]},{"start_timestamp":"2025-03-11T20:38:36.948Z","before":[{"result":{"duration":1495938400,"status":"passed"},"match":{"location":"recupera.steps.hooks.hook.setUp()"}}],"line":10,"name":"Fazer login com usuario valido","description":"","id":"login-valido;fazer-login-com-usuario-valido","after":[{"result":{"duration":495817500,"status":"passed"},"match":{"location":"recupera.steps.hooks.hook.finish()"}}],"type":"scenario","keyword":"Cenario","steps":[{"result":{"duration":1631453800,"status":"passed"},"line":11,"name":"faço login com dados validos","match":{"location":"recupera.steps.HomeStep.facologincomdadosvalidos()"},"keyword":"Quando "},{"result":{"duration":301624700,"status":"passed"},"line":12,"name":"realizo login com sucesso","match":{"location":"recupera.steps.HomeStep.realizoLoginComSucesso()"},"keyword":"Entao "}],"tags":[{"name":"@LoginExecution"},{"name":"@CenarioComum"}]}],"name":"Login valido","description":"","id":"login-valido","keyword":"Funcionalidade","uri":"file:src/test/resources/features/Login.feature","tags":[{"name":"@LoginExecution","type":"Tag","location":{"line":3,"column":1}}]}]